<annotation>
	<folder>normal</folder>
	<filename>no_0165.jpg</filename>
	<path>/home/duycuong/PycharmProjects/ocr/viText/viText/viData/viReceipts/split/images/normal/no_0165.jpg</path>
	<source>
		<database>Unknown</database>
	</source>
	<size>
		<width>1793</width>
		<height>5573</height>
		<depth>3</depth>
	</size>
	<segmented>0</segmented>
	<object>
		<name>0.85498923</name>
		<pose>Unspecified</pose>
		<truncated>0</truncated>
		<difficult>0</difficult>
		<bndbox>
			<xmin>370</xmin>
			<ymin>5226</ymin>
			<xmax>459</xmax>
			<ymax>5292</ymax>
		</bndbox>
	</object>
	<object>
		<name>0.88010234</name>
		<pose>Unspecified</pose>
		<truncated>0</truncated>
		<difficult>0</difficult>
		<bndbox>
			<xmin>189</xmin>
			<ymin>5213</ymin>
			<xmax>341</xmax>
			<ymax>5294</ymax>
		</bndbox>
	</object>
	<object>
		<name>0.8869509</name>
		<pose>Unspecified</pose>
		<truncated>0</truncated>
		<difficult>0</difficult>
		<bndbox>
			<xmin>822</xmin>
			<ymin>5211</ymin>
			<xmax>974</xmax>
			<ymax>5281</ymax>
		</bndbox>
	</object>
	<object>
		<name>0.91440153</name>
		<pose>Unspecified</pose>
		<truncated>0</truncated>
		<difficult>0</difficult>
		<bndbox>
			<xmin>680</xmin>
			<ymin>5209</ymin>
			<xmax>792</xmax>
			<ymax>5276</ymax>
		</bndbox>
	</object>
	<object>
		<name>0.8771629</name>
		<pose>Unspecified</pose>
		<truncated>0</truncated>
		<difficult>0</difficult>
		<bndbox>
			<xmin>1238</xmin>
			<ymin>5208</ymin>
			<xmax>1389</xmax>
			<ymax>5268</ymax>
		</bndbox>
	</object>
	<object>
		<name>0.8631424</name>
		<pose>Unspecified</pose>
		<truncated>0</truncated>
		<difficult>0</difficult>
		<bndbox>
			<xmin>1439</xmin>
			<ymin>5198</ymin>
			<xmax>1504</xmax>
			<ymax>5270</ymax>
		</bndbox>
	</object>
	<object>
		<name>0.87150264</name>
		<pose>Unspecified</pose>
		<truncated>0</truncated>
		<difficult>0</difficult>
		<bndbox>
			<xmin>153</xmin>
			<ymin>5033</ymin>
			<xmax>332</xmax>
			<ymax>5100</ymax>
		</bndbox>
	</object>
	<object>
		<name>0.91886187</name>
		<pose>Unspecified</pose>
		<truncated>0</truncated>
		<difficult>0</difficult>
		<bndbox>
			<xmin>372</xmin>
			<ymin>5027</ymin>
			<xmax>484</xmax>
			<ymax>5096</ymax>
		</bndbox>
	</object>
	<object>
		<name>0.88016707</name>
		<pose>Unspecified</pose>
		<truncated>0</truncated>
		<difficult>0</difficult>
		<bndbox>
			<xmin>525</xmin>
			<ymin>5026</ymin>
			<xmax>612</xmax>
			<ymax>5097</ymax>
		</bndbox>
	</object>
	<object>
		<name>0.8789745</name>
		<pose>Unspecified</pose>
		<truncated>0</truncated>
		<difficult>0</difficult>
		<bndbox>
			<xmin>1125</xmin>
			<ymin>5026</ymin>
			<xmax>1311</xmax>
			<ymax>5082</ymax>
		</bndbox>
	</object>
	<object>
		<name>0.8964304</name>
		<pose>Unspecified</pose>
		<truncated>0</truncated>
		<difficult>0</difficult>
		<bndbox>
			<xmin>817</xmin>
			<ymin>5024</ymin>
			<xmax>934</xmax>
			<ymax>5091</ymax>
		</bndbox>
	</object>
	<object>
		<name>0.8945084</name>
		<pose>Unspecified</pose>
		<truncated>0</truncated>
		<difficult>0</difficult>
		<bndbox>
			<xmin>640</xmin>
			<ymin>5023</ymin>
			<xmax>788</xmax>
			<ymax>5091</ymax>
		</bndbox>
	</object>
	<object>
		<name>0.8671071</name>
		<pose>Unspecified</pose>
		<truncated>0</truncated>
		<difficult>0</difficult>
		<bndbox>
			<xmin>967</xmin>
			<ymin>5018</ymin>
			<xmax>1091</xmax>
			<ymax>5089</ymax>
		</bndbox>
	</object>
	<object>
		<name>0.8605243</name>
		<pose>Unspecified</pose>
		<truncated>0</truncated>
		<difficult>0</difficult>
		<bndbox>
			<xmin>1351</xmin>
			<ymin>5018</ymin>
			<xmax>1430</xmax>
			<ymax>5086</ymax>
		</bndbox>
	</object>
	<object>
		<name>0.8684193</name>
		<pose>Unspecified</pose>
		<truncated>0</truncated>
		<difficult>0</difficult>
		<bndbox>
			<xmin>145</xmin>
			<ymin>4935</ymin>
			<xmax>294</xmax>
			<ymax>5012</ymax>
		</bndbox>
	</object>
	<object>
		<name>0.89311695</name>
		<pose>Unspecified</pose>
		<truncated>0</truncated>
		<difficult>0</difficult>
		<bndbox>
			<xmin>487</xmin>
			<ymin>4935</ymin>
			<xmax>632</xmax>
			<ymax>5009</ymax>
		</bndbox>
	</object>
	<object>
		<name>0.8418749</name>
		<pose>Unspecified</pose>
		<truncated>0</truncated>
		<difficult>0</difficult>
		<bndbox>
			<xmin>324</xmin>
			<ymin>4931</ymin>
			<xmax>454</xmax>
			<ymax>5010</ymax>
		</bndbox>
	</object>
	<object>
		<name>0.92657185</name>
		<pose>Unspecified</pose>
		<truncated>0</truncated>
		<difficult>0</difficult>
		<bndbox>
			<xmin>668</xmin>
			<ymin>4928</ymin>
			<xmax>786</xmax>
			<ymax>4999</ymax>
		</bndbox>
	</object>
	<object>
		<name>0.8608632</name>
		<pose>Unspecified</pose>
		<truncated>0</truncated>
		<difficult>0</difficult>
		<bndbox>
			<xmin>1164</xmin>
			<ymin>4850</ymin>
			<xmax>1311</xmax>
			<ymax>4901</ymax>
		</bndbox>
	</object>
	<object>
		<name>0.873936</name>
		<pose>Unspecified</pose>
		<truncated>0</truncated>
		<difficult>0</difficult>
		<bndbox>
			<xmin>402</xmin>
			<ymin>4839</ymin>
			<xmax>532</xmax>
			<ymax>4917</ymax>
		</bndbox>
	</object>
	<object>
		<name>0.83598995</name>
		<pose>Unspecified</pose>
		<truncated>0</truncated>
		<difficult>0</difficult>
		<bndbox>
			<xmin>147</xmin>
			<ymin>4834</ymin>
			<xmax>373</xmax>
			<ymax>4916</ymax>
		</bndbox>
	</object>
	<object>
		<name>0.8744568</name>
		<pose>Unspecified</pose>
		<truncated>0</truncated>
		<difficult>0</difficult>
		<bndbox>
			<xmin>929</xmin>
			<ymin>4836</ymin>
			<xmax>1124</xmax>
			<ymax>4906</ymax>
		</bndbox>
	</object>
	<object>
		<name>0.88800335</name>
		<pose>Unspecified</pose>
		<truncated>0</truncated>
		<difficult>0</difficult>
		<bndbox>
			<xmin>713</xmin>
			<ymin>4838</ymin>
			<xmax>896</xmax>
			<ymax>4898</ymax>
		</bndbox>
	</object>
	<object>
		<name>0.91171896</name>
		<pose>Unspecified</pose>
		<truncated>0</truncated>
		<difficult>0</difficult>
		<bndbox>
			<xmin>569</xmin>
			<ymin>4830</ymin>
			<xmax>679</xmax>
			<ymax>4916</ymax>
		</bndbox>
	</object>
	<object>
		<name>0.8818007</name>
		<pose>Unspecified</pose>
		<truncated>0</truncated>
		<difficult>0</difficult>
		<bndbox>
			<xmin>1345</xmin>
			<ymin>4827</ymin>
			<xmax>1466</xmax>
			<ymax>4907</ymax>
		</bndbox>
	</object>
	<object>
		<name>0.62248546</name>
		<pose>Unspecified</pose>
		<truncated>0</truncated>
		<difficult>0</difficult>
		<bndbox>
			<xmin>137</xmin>
			<ymin>4373</ymin>
			<xmax>1086</xmax>
			<ymax>4441</ymax>
		</bndbox>
	</object>
	<object>
		<name>0.88401973</name>
		<pose>Unspecified</pose>
		<truncated>0</truncated>
		<difficult>0</difficult>
		<bndbox>
			<xmin>356</xmin>
			<ymin>4290</ymin>
			<xmax>447</xmax>
			<ymax>4343</ymax>
		</bndbox>
	</object>
	<object>
		<name>0.8949596</name>
		<pose>Unspecified</pose>
		<truncated>0</truncated>
		<difficult>0</difficult>
		<bndbox>
			<xmin>132</xmin>
			<ymin>4284</ymin>
			<xmax>323</xmax>
			<ymax>4347</ymax>
		</bndbox>
	</object>
	<object>
		<name>0.8665778</name>
		<pose>Unspecified</pose>
		<truncated>0</truncated>
		<difficult>0</difficult>
		<bndbox>
			<xmin>780</xmin>
			<ymin>4281</ymin>
			<xmax>960</xmax>
			<ymax>4343</ymax>
		</bndbox>
	</object>
	<object>
		<name>0.9022281</name>
		<pose>Unspecified</pose>
		<truncated>0</truncated>
		<difficult>0</difficult>
		<bndbox>
			<xmin>624</xmin>
			<ymin>4271</ymin>
			<xmax>746</xmax>
			<ymax>4352</ymax>
		</bndbox>
	</object>
	<object>
		<name>0.8956188</name>
		<pose>Unspecified</pose>
		<truncated>0</truncated>
		<difficult>0</difficult>
		<bndbox>
			<xmin>475</xmin>
			<ymin>4275</ymin>
			<xmax>590</xmax>
			<ymax>4341</ymax>
		</bndbox>
	</object>
	<object>
		<name>0.87958306</name>
		<pose>Unspecified</pose>
		<truncated>0</truncated>
		<difficult>0</difficult>
		<bndbox>
			<xmin>1007</xmin>
			<ymin>4270</ymin>
			<xmax>1117</xmax>
			<ymax>4343</ymax>
		</bndbox>
	</object>
	<object>
		<name>0.8051013</name>
		<pose>Unspecified</pose>
		<truncated>0</truncated>
		<difficult>0</difficult>
		<bndbox>
			<xmin>1190</xmin>
			<ymin>4269</ymin>
			<xmax>1462</xmax>
			<ymax>4337</ymax>
		</bndbox>
	</object>
	<object>
		<name>0.6346594</name>
		<pose>Unspecified</pose>
		<truncated>0</truncated>
		<difficult>0</difficult>
		<bndbox>
			<xmin>1130</xmin>
			<ymin>4281</ymin>
			<xmax>1153</xmax>
			<ymax>4331</ymax>
		</bndbox>
	</object>
	<object>
		<name>0.86668617</name>
		<pose>Unspecified</pose>
		<truncated>0</truncated>
		<difficult>0</difficult>
		<bndbox>
			<xmin>244</xmin>
			<ymin>4179</ymin>
			<xmax>401</xmax>
			<ymax>4255</ymax>
		</bndbox>
	</object>
	<object>
		<name>0.8885025</name>
		<pose>Unspecified</pose>
		<truncated>0</truncated>
		<difficult>0</difficult>
		<bndbox>
			<xmin>562</xmin>
			<ymin>4183</ymin>
			<xmax>738</xmax>
			<ymax>4239</ymax>
		</bndbox>
	</object>
	<object>
		<name>0.9102982</name>
		<pose>Unspecified</pose>
		<truncated>0</truncated>
		<difficult>0</difficult>
		<bndbox>
			<xmin>126</xmin>
			<ymin>4180</ymin>
			<xmax>215</xmax>
			<ymax>4253</ymax>
		</bndbox>
	</object>
	<object>
		<name>0.80697936</name>
		<pose>Unspecified</pose>
		<truncated>0</truncated>
		<difficult>0</difficult>
		<bndbox>
			<xmin>963</xmin>
			<ymin>4174</ymin>
			<xmax>1272</xmax>
			<ymax>4244</ymax>
		</bndbox>
	</object>
	<object>
		<name>0.8297153</name>
		<pose>Unspecified</pose>
		<truncated>0</truncated>
		<difficult>0</difficult>
		<bndbox>
			<xmin>774</xmin>
			<ymin>4177</ymin>
			<xmax>926</xmax>
			<ymax>4240</ymax>
		</bndbox>
	</object>
	<object>
		<name>0.8950051</name>
		<pose>Unspecified</pose>
		<truncated>0</truncated>
		<difficult>0</difficult>
		<bndbox>
			<xmin>1423</xmin>
			<ymin>4169</ymin>
			<xmax>1541</xmax>
			<ymax>4250</ymax>
		</bndbox>
	</object>
	<object>
		<name>0.9053551</name>
		<pose>Unspecified</pose>
		<truncated>0</truncated>
		<difficult>0</difficult>
		<bndbox>
			<xmin>426</xmin>
			<ymin>4171</ymin>
			<xmax>522</xmax>
			<ymax>4247</ymax>
		</bndbox>
	</object>
	<object>
		<name>0.9085234</name>
		<pose>Unspecified</pose>
		<truncated>0</truncated>
		<difficult>0</difficult>
		<bndbox>
			<xmin>1304</xmin>
			<ymin>4167</ymin>
			<xmax>1391</xmax>
			<ymax>4240</ymax>
		</bndbox>
	</object>
	<object>
		<name>0.9112029</name>
		<pose>Unspecified</pose>
		<truncated>0</truncated>
		<difficult>0</difficult>
		<bndbox>
			<xmin>356</xmin>
			<ymin>4093</ymin>
			<xmax>478</xmax>
			<ymax>4160</ymax>
		</bndbox>
	</object>
	<object>
		<name>0.92356825</name>
		<pose>Unspecified</pose>
		<truncated>0</truncated>
		<difficult>0</difficult>
		<bndbox>
			<xmin>517</xmin>
			<ymin>4090</ymin>
			<xmax>666</xmax>
			<ymax>4160</ymax>
		</bndbox>
	</object>
	<object>
		<name>0.35871372</name>
		<pose>Unspecified</pose>
		<truncated>0</truncated>
		<difficult>0</difficult>
		<bndbox>
			<xmin>133</xmin>
			<ymin>4101</ymin>
			<xmax>174</xmax>
			<ymax>4150</ymax>
		</bndbox>
	</object>
	<object>
		<name>0.8628653</name>
		<pose>Unspecified</pose>
		<truncated>0</truncated>
		<difficult>0</difficult>
		<bndbox>
			<xmin>205</xmin>
			<ymin>4083</ymin>
			<xmax>318</xmax>
			<ymax>4158</ymax>
		</bndbox>
	</object>
	<object>
		<name>0.8688664</name>
		<pose>Unspecified</pose>
		<truncated>0</truncated>
		<difficult>0</difficult>
		<bndbox>
			<xmin>1119</xmin>
			<ymin>4082</ymin>
			<xmax>1312</xmax>
			<ymax>4149</ymax>
		</bndbox>
	</object>
	<object>
		<name>0.81886876</name>
		<pose>Unspecified</pose>
		<truncated>0</truncated>
		<difficult>0</difficult>
		<bndbox>
			<xmin>851</xmin>
			<ymin>4084</ymin>
			<xmax>1076</xmax>
			<ymax>4141</ymax>
		</bndbox>
	</object>
	<object>
		<name>0.87167627</name>
		<pose>Unspecified</pose>
		<truncated>0</truncated>
		<difficult>0</difficult>
		<bndbox>
			<xmin>700</xmin>
			<ymin>4077</ymin>
			<xmax>817</xmax>
			<ymax>4149</ymax>
		</bndbox>
	</object>
	<object>
		<name>0.8130637</name>
		<pose>Unspecified</pose>
		<truncated>0</truncated>
		<difficult>0</difficult>
		<bndbox>
			<xmin>1340</xmin>
			<ymin>4080</ymin>
			<xmax>1418</xmax>
			<ymax>4147</ymax>
		</bndbox>
	</object>
	<object>
		<name>0.87961555</name>
		<pose>Unspecified</pose>
		<truncated>0</truncated>
		<difficult>0</difficult>
		<bndbox>
			<xmin>1525</xmin>
			<ymin>4071</ymin>
			<xmax>1644</xmax>
			<ymax>4153</ymax>
		</bndbox>
	</object>
	<object>
		<name>0.88132244</name>
		<pose>Unspecified</pose>
		<truncated>0</truncated>
		<difficult>0</difficult>
		<bndbox>
			<xmin>1415</xmin>
			<ymin>4071</ymin>
			<xmax>1502</xmax>
			<ymax>4146</ymax>
		</bndbox>
	</object>
	<object>
		<name>0.76412565</name>
		<pose>Unspecified</pose>
		<truncated>0</truncated>
		<difficult>0</difficult>
		<bndbox>
			<xmin>511</xmin>
			<ymin>3898</ymin>
			<xmax>630</xmax>
			<ymax>3971</ymax>
		</bndbox>
	</object>
	<object>
		<name>0.87680227</name>
		<pose>Unspecified</pose>
		<truncated>0</truncated>
		<difficult>0</difficult>
		<bndbox>
			<xmin>655</xmin>
			<ymin>3892</ymin>
			<xmax>780</xmax>
			<ymax>3965</ymax>
		</bndbox>
	</object>
	<object>
		<name>0.88222444</name>
		<pose>Unspecified</pose>
		<truncated>0</truncated>
		<difficult>0</difficult>
		<bndbox>
			<xmin>354</xmin>
			<ymin>3888</ymin>
			<xmax>482</xmax>
			<ymax>3964</ymax>
		</bndbox>
	</object>
	<object>
		<name>0.9097918</name>
		<pose>Unspecified</pose>
		<truncated>0</truncated>
		<difficult>0</difficult>
		<bndbox>
			<xmin>805</xmin>
			<ymin>3886</ymin>
			<xmax>928</xmax>
			<ymax>3967</ymax>
		</bndbox>
	</object>
	<object>
		<name>0.8967547</name>
		<pose>Unspecified</pose>
		<truncated>0</truncated>
		<difficult>0</difficult>
		<bndbox>
			<xmin>1268</xmin>
			<ymin>3886</ymin>
			<xmax>1489</xmax>
			<ymax>3951</ymax>
		</bndbox>
	</object>
	<object>
		<name>0.80508584</name>
		<pose>Unspecified</pose>
		<truncated>0</truncated>
		<difficult>0</difficult>
		<bndbox>
			<xmin>959</xmin>
			<ymin>3887</ymin>
			<xmax>1076</xmax>
			<ymax>3966</ymax>
		</bndbox>
	</object>
	<object>
		<name>0.8577232</name>
		<pose>Unspecified</pose>
		<truncated>0</truncated>
		<difficult>0</difficult>
		<bndbox>
			<xmin>1111</xmin>
			<ymin>3878</ymin>
			<xmax>1239</xmax>
			<ymax>3967</ymax>
		</bndbox>
	</object>
	<object>
		<name>0.8362241</name>
		<pose>Unspecified</pose>
		<truncated>0</truncated>
		<difficult>0</difficult>
		<bndbox>
			<xmin>555</xmin>
			<ymin>3596</ymin>
			<xmax>728</xmax>
			<ymax>3728</ymax>
		</bndbox>
	</object>
	<object>
		<name>0.867164</name>
		<pose>Unspecified</pose>
		<truncated>0</truncated>
		<difficult>0</difficult>
		<bndbox>
			<xmin>313</xmin>
			<ymin>3599</ymin>
			<xmax>521</xmax>
			<ymax>3723</ymax>
		</bndbox>
	</object>
	<object>
		<name>0.8342563</name>
		<pose>Unspecified</pose>
		<truncated>0</truncated>
		<difficult>0</difficult>
		<bndbox>
			<xmin>126</xmin>
			<ymin>3587</ymin>
			<xmax>281</xmax>
			<ymax>3743</ymax>
		</bndbox>
	</object>
	<object>
		<name>0.6749048</name>
		<pose>Unspecified</pose>
		<truncated>0</truncated>
		<difficult>0</difficult>
		<bndbox>
			<xmin>1394</xmin>
			<ymin>3577</ymin>
			<xmax>1737</xmax>
			<ymax>3711</ymax>
		</bndbox>
	</object>
	<object>
		<name>0.48291445</name>
		<pose>Unspecified</pose>
		<truncated>0</truncated>
		<difficult>0</difficult>
		<bndbox>
			<xmin>282</xmin>
			<ymin>3249</ymin>
			<xmax>307</xmax>
			<ymax>3303</ymax>
		</bndbox>
	</object>
	<object>
		<name>0.94413334</name>
		<pose>Unspecified</pose>
		<truncated>0</truncated>
		<difficult>0</difficult>
		<bndbox>
			<xmin>117</xmin>
			<ymin>3239</ymin>
			<xmax>271</xmax>
			<ymax>3315</ymax>
		</bndbox>
	</object>
	<object>
		<name>0.8374608</name>
		<pose>Unspecified</pose>
		<truncated>0</truncated>
		<difficult>0</difficult>
		<bndbox>
			<xmin>1386</xmin>
			<ymin>3230</ymin>
			<xmax>1721</xmax>
			<ymax>3295</ymax>
		</bndbox>
	</object>
	<object>
		<name>0.38765532</name>
		<pose>Unspecified</pose>
		<truncated>0</truncated>
		<difficult>0</difficult>
		<bndbox>
			<xmin>242</xmin>
			<ymin>3049</ymin>
			<xmax>266</xmax>
			<ymax>3105</ymax>
		</bndbox>
	</object>
	<object>
		<name>0.8806689</name>
		<pose>Unspecified</pose>
		<truncated>0</truncated>
		<difficult>0</difficult>
		<bndbox>
			<xmin>109</xmin>
			<ymin>3040</ymin>
			<xmax>230</xmax>
			<ymax>3115</ymax>
		</bndbox>
	</object>
	<object>
		<name>0.8478018</name>
		<pose>Unspecified</pose>
		<truncated>0</truncated>
		<difficult>0</difficult>
		<bndbox>
			<xmin>1471</xmin>
			<ymin>3034</ymin>
			<xmax>1718</xmax>
			<ymax>3096</ymax>
		</bndbox>
	</object>
	<object>
		<name>0.53447956</name>
		<pose>Unspecified</pose>
		<truncated>0</truncated>
		<difficult>0</difficult>
		<bndbox>
			<xmin>475</xmin>
			<ymin>2855</ymin>
			<xmax>494</xmax>
			<ymax>2909</ymax>
		</bndbox>
	</object>
	<object>
		<name>0.8891337</name>
		<pose>Unspecified</pose>
		<truncated>0</truncated>
		<difficult>0</difficult>
		<bndbox>
			<xmin>109</xmin>
			<ymin>2847</ymin>
			<xmax>266</xmax>
			<ymax>2928</ymax>
		</bndbox>
	</object>
	<object>
		<name>0.8621336</name>
		<pose>Unspecified</pose>
		<truncated>0</truncated>
		<difficult>0</difficult>
		<bndbox>
			<xmin>301</xmin>
			<ymin>2848</ymin>
			<xmax>465</xmax>
			<ymax>2929</ymax>
		</bndbox>
	</object>
	<object>
		<name>0.7844833</name>
		<pose>Unspecified</pose>
		<truncated>0</truncated>
		<difficult>0</difficult>
		<bndbox>
			<xmin>1387</xmin>
			<ymin>2838</ymin>
			<xmax>1720</xmax>
			<ymax>2908</ymax>
		</bndbox>
	</object>
	<object>
		<name>0.79450274</name>
		<pose>Unspecified</pose>
		<truncated>0</truncated>
		<difficult>0</difficult>
		<bndbox>
			<xmin>261</xmin>
			<ymin>2663</ymin>
			<xmax>452</xmax>
			<ymax>2725</ymax>
		</bndbox>
	</object>
	<object>
		<name>0.86832166</name>
		<pose>Unspecified</pose>
		<truncated>0</truncated>
		<difficult>0</difficult>
		<bndbox>
			<xmin>493</xmin>
			<ymin>2664</ymin>
			<xmax>576</xmax>
			<ymax>2720</ymax>
		</bndbox>
	</object>
	<object>
		<name>0.9208305</name>
		<pose>Unspecified</pose>
		<truncated>0</truncated>
		<difficult>0</difficult>
		<bndbox>
			<xmin>103</xmin>
			<ymin>2653</ymin>
			<xmax>224</xmax>
			<ymax>2724</ymax>
		</bndbox>
	</object>
	<object>
		<name>0.8906205</name>
		<pose>Unspecified</pose>
		<truncated>0</truncated>
		<difficult>0</difficult>
		<bndbox>
			<xmin>764</xmin>
			<ymin>2650</ymin>
			<xmax>882</xmax>
			<ymax>2731</ymax>
		</bndbox>
	</object>
	<object>
		<name>0.87893325</name>
		<pose>Unspecified</pose>
		<truncated>0</truncated>
		<difficult>0</difficult>
		<bndbox>
			<xmin>609</xmin>
			<ymin>2643</ymin>
			<xmax>725</xmax>
			<ymax>2726</ymax>
		</bndbox>
	</object>
	<object>
		<name>0.84051734</name>
		<pose>Unspecified</pose>
		<truncated>0</truncated>
		<difficult>0</difficult>
		<bndbox>
			<xmin>1467</xmin>
			<ymin>2647</ymin>
			<xmax>1717</xmax>
			<ymax>2707</ymax>
		</bndbox>
	</object>
	<object>
		<name>0.7009538</name>
		<pose>Unspecified</pose>
		<truncated>0</truncated>
		<difficult>0</difficult>
		<bndbox>
			<xmin>1268</xmin>
			<ymin>2648</ymin>
			<xmax>1298</xmax>
			<ymax>2709</ymax>
		</bndbox>
	</object>
	<object>
		<name>0.3703068</name>
		<pose>Unspecified</pose>
		<truncated>0</truncated>
		<difficult>0</difficult>
		<bndbox>
			<xmin>1277</xmin>
			<ymin>2541</ymin>
			<xmax>1307</xmax>
			<ymax>2608</ymax>
		</bndbox>
	</object>
	<object>
		<name>0.9236052</name>
		<pose>Unspecified</pose>
		<truncated>0</truncated>
		<difficult>0</difficult>
		<bndbox>
			<xmin>100</xmin>
			<ymin>2553</ymin>
			<xmax>223</xmax>
			<ymax>2625</ymax>
		</bndbox>
	</object>
	<object>
		<name>0.90383375</name>
		<pose>Unspecified</pose>
		<truncated>0</truncated>
		<difficult>0</difficult>
		<bndbox>
			<xmin>367</xmin>
			<ymin>2552</ymin>
			<xmax>458</xmax>
			<ymax>2623</ymax>
		</bndbox>
	</object>
	<object>
		<name>0.91340786</name>
		<pose>Unspecified</pose>
		<truncated>0</truncated>
		<difficult>0</difficult>
		<bndbox>
			<xmin>249</xmin>
			<ymin>2550</ymin>
			<xmax>338</xmax>
			<ymax>2623</ymax>
		</bndbox>
	</object>
	<object>
		<name>0.82737696</name>
		<pose>Unspecified</pose>
		<truncated>0</truncated>
		<difficult>0</difficult>
		<bndbox>
			<xmin>1494</xmin>
			<ymin>2548</ymin>
			<xmax>1717</xmax>
			<ymax>2609</ymax>
		</bndbox>
	</object>
	<object>
		<name>0.37754357</name>
		<pose>Unspecified</pose>
		<truncated>0</truncated>
		<difficult>0</difficult>
		<bndbox>
			<xmin>1274</xmin>
			<ymin>2452</ymin>
			<xmax>1301</xmax>
			<ymax>2512</ymax>
		</bndbox>
	</object>
	<object>
		<name>0.86984044</name>
		<pose>Unspecified</pose>
		<truncated>0</truncated>
		<difficult>0</difficult>
		<bndbox>
			<xmin>412</xmin>
			<ymin>2469</ymin>
			<xmax>534</xmax>
			<ymax>2519</ymax>
		</bndbox>
	</object>
	<object>
		<name>0.90504605</name>
		<pose>Unspecified</pose>
		<truncated>0</truncated>
		<difficult>0</difficult>
		<bndbox>
			<xmin>251</xmin>
			<ymin>2457</ymin>
			<xmax>375</xmax>
			<ymax>2522</ymax>
		</bndbox>
	</object>
	<object>
		<name>0.8967464</name>
		<pose>Unspecified</pose>
		<truncated>0</truncated>
		<difficult>0</difficult>
		<bndbox>
			<xmin>100</xmin>
			<ymin>2452</ymin>
			<xmax>223</xmax>
			<ymax>2525</ymax>
		</bndbox>
	</object>
	<object>
		<name>0.832506</name>
		<pose>Unspecified</pose>
		<truncated>0</truncated>
		<difficult>0</difficult>
		<bndbox>
			<xmin>1494</xmin>
			<ymin>2446</ymin>
			<xmax>1718</xmax>
			<ymax>2509</ymax>
		</bndbox>
	</object>
	<object>
		<name>0.40332365</name>
		<pose>Unspecified</pose>
		<truncated>0</truncated>
		<difficult>0</difficult>
		<bndbox>
			<xmin>1277</xmin>
			<ymin>2345</ymin>
			<xmax>1304</xmax>
			<ymax>2412</ymax>
		</bndbox>
	</object>
	<object>
		<name>0.8976581</name>
		<pose>Unspecified</pose>
		<truncated>0</truncated>
		<difficult>0</difficult>
		<bndbox>
			<xmin>451</xmin>
			<ymin>2351</ymin>
			<xmax>571</xmax>
			<ymax>2430</ymax>
		</bndbox>
	</object>
	<object>
		<name>0.91441023</name>
		<pose>Unspecified</pose>
		<truncated>0</truncated>
		<difficult>0</difficult>
		<bndbox>
			<xmin>260</xmin>
			<ymin>2352</ymin>
			<xmax>414</xmax>
			<ymax>2431</ymax>
		</bndbox>
	</object>
	<object>
		<name>0.9055307</name>
		<pose>Unspecified</pose>
		<truncated>0</truncated>
		<difficult>0</difficult>
		<bndbox>
			<xmin>96</xmin>
			<ymin>2354</ymin>
			<xmax>221</xmax>
			<ymax>2426</ymax>
		</bndbox>
	</object>
	<object>
		<name>0.9009794</name>
		<pose>Unspecified</pose>
		<truncated>0</truncated>
		<difficult>0</difficult>
		<bndbox>
			<xmin>601</xmin>
			<ymin>2346</ymin>
			<xmax>724</xmax>
			<ymax>2420</ymax>
		</bndbox>
	</object>
	<object>
		<name>0.85027695</name>
		<pose>Unspecified</pose>
		<truncated>0</truncated>
		<difficult>0</difficult>
		<bndbox>
			<xmin>1496</xmin>
			<ymin>2345</ymin>
			<xmax>1718</xmax>
			<ymax>2410</ymax>
		</bndbox>
	</object>
	<object>
		<name>0.90069515</name>
		<pose>Unspecified</pose>
		<truncated>0</truncated>
		<difficult>0</difficult>
		<bndbox>
			<xmin>760</xmin>
			<ymin>2345</ymin>
			<xmax>879</xmax>
			<ymax>2420</ymax>
		</bndbox>
	</object>
	<object>
		<name>0.8755714</name>
		<pose>Unspecified</pose>
		<truncated>0</truncated>
		<difficult>0</difficult>
		<bndbox>
			<xmin>903</xmin>
			<ymin>2339</ymin>
			<xmax>996</xmax>
			<ymax>2421</ymax>
		</bndbox>
	</object>
	<object>
		<name>0.90638894</name>
		<pose>Unspecified</pose>
		<truncated>0</truncated>
		<difficult>0</difficult>
		<bndbox>
			<xmin>101</xmin>
			<ymin>2259</ymin>
			<xmax>254</xmax>
			<ymax>2322</ymax>
		</bndbox>
	</object>
	<object>
		<name>0.8756727</name>
		<pose>Unspecified</pose>
		<truncated>0</truncated>
		<difficult>0</difficult>
		<bndbox>
			<xmin>291</xmin>
			<ymin>2247</ymin>
			<xmax>411</xmax>
			<ymax>2322</ymax>
		</bndbox>
	</object>
	<object>
		<name>0.86969775</name>
		<pose>Unspecified</pose>
		<truncated>0</truncated>
		<difficult>0</difficult>
		<bndbox>
			<xmin>1499</xmin>
			<ymin>2245</ymin>
			<xmax>1718</xmax>
			<ymax>2311</ymax>
		</bndbox>
	</object>
	<object>
		<name>0.7739763</name>
		<pose>Unspecified</pose>
		<truncated>0</truncated>
		<difficult>0</difficult>
		<bndbox>
			<xmin>1259</xmin>
			<ymin>2239</ymin>
			<xmax>1307</xmax>
			<ymax>2317</ymax>
		</bndbox>
	</object>
	<object>
		<name>0.8879312</name>
		<pose>Unspecified</pose>
		<truncated>0</truncated>
		<difficult>0</difficult>
		<bndbox>
			<xmin>98</xmin>
			<ymin>2154</ymin>
			<xmax>282</xmax>
			<ymax>2233</ymax>
		</bndbox>
	</object>
	<object>
		<name>0.906422</name>
		<pose>Unspecified</pose>
		<truncated>0</truncated>
		<difficult>0</difficult>
		<bndbox>
			<xmin>336</xmin>
			<ymin>2154</ymin>
			<xmax>454</xmax>
			<ymax>2225</ymax>
		</bndbox>
	</object>
	<object>
		<name>0.7382603</name>
		<pose>Unspecified</pose>
		<truncated>0</truncated>
		<difficult>0</difficult>
		<bndbox>
			<xmin>1687</xmin>
			<ymin>2147</ymin>
			<xmax>1728</xmax>
			<ymax>2208</ymax>
		</bndbox>
	</object>
	<object>
		<name>0.7480944</name>
		<pose>Unspecified</pose>
		<truncated>0</truncated>
		<difficult>0</difficult>
		<bndbox>
			<xmin>1262</xmin>
			<ymin>2143</ymin>
			<xmax>1304</xmax>
			<ymax>2217</ymax>
		</bndbox>
	</object>
	<object>
		<name>0.8650095</name>
		<pose>Unspecified</pose>
		<truncated>0</truncated>
		<difficult>0</difficult>
		<bndbox>
			<xmin>297</xmin>
			<ymin>2062</ymin>
			<xmax>450</xmax>
			<ymax>2119</ymax>
		</bndbox>
	</object>
	<object>
		<name>0.41132683</name>
		<pose>Unspecified</pose>
		<truncated>0</truncated>
		<difficult>0</difficult>
		<bndbox>
			<xmin>1276</xmin>
			<ymin>2068</ymin>
			<xmax>1292</xmax>
			<ymax>2110</ymax>
		</bndbox>
	</object>
	<object>
		<name>0.880868</name>
		<pose>Unspecified</pose>
		<truncated>0</truncated>
		<difficult>0</difficult>
		<bndbox>
			<xmin>92</xmin>
			<ymin>2054</ymin>
			<xmax>251</xmax>
			<ymax>2124</ymax>
		</bndbox>
	</object>
	<object>
		<name>0.90729165</name>
		<pose>Unspecified</pose>
		<truncated>0</truncated>
		<difficult>0</difficult>
		<bndbox>
			<xmin>487</xmin>
			<ymin>2051</ymin>
			<xmax>609</xmax>
			<ymax>2123</ymax>
		</bndbox>
	</object>
	<object>
		<name>0.8175351</name>
		<pose>Unspecified</pose>
		<truncated>0</truncated>
		<difficult>0</difficult>
		<bndbox>
			<xmin>1468</xmin>
			<ymin>2046</ymin>
			<xmax>1718</xmax>
			<ymax>2112</ymax>
		</bndbox>
	</object>
	<object>
		<name>0.8465945</name>
		<pose>Unspecified</pose>
		<truncated>0</truncated>
		<difficult>0</difficult>
		<bndbox>
			<xmin>370</xmin>
			<ymin>1972</ymin>
			<xmax>525</xmax>
			<ymax>2028</ymax>
		</bndbox>
	</object>
	<object>
		<name>0.8865301</name>
		<pose>Unspecified</pose>
		<truncated>0</truncated>
		<difficult>0</difficult>
		<bndbox>
			<xmin>560</xmin>
			<ymin>1969</ymin>
			<xmax>680</xmax>
			<ymax>2030</ymax>
		</bndbox>
	</object>
	<object>
		<name>0.8952162</name>
		<pose>Unspecified</pose>
		<truncated>0</truncated>
		<difficult>0</difficult>
		<bndbox>
			<xmin>92</xmin>
			<ymin>1956</ymin>
			<xmax>215</xmax>
			<ymax>2037</ymax>
		</bndbox>
	</object>
	<object>
		<name>0.8866675</name>
		<pose>Unspecified</pose>
		<truncated>0</truncated>
		<difficult>0</difficult>
		<bndbox>
			<xmin>251</xmin>
			<ymin>1958</ymin>
			<xmax>332</xmax>
			<ymax>2035</ymax>
		</bndbox>
	</object>
	<object>
		<name>0.8587227</name>
		<pose>Unspecified</pose>
		<truncated>0</truncated>
		<difficult>0</difficult>
		<bndbox>
			<xmin>1469</xmin>
			<ymin>1950</ymin>
			<xmax>1718</xmax>
			<ymax>2011</ymax>
		</bndbox>
	</object>
	<object>
		<name>0.5064465</name>
		<pose>Unspecified</pose>
		<truncated>0</truncated>
		<difficult>0</difficult>
		<bndbox>
			<xmin>1275</xmin>
			<ymin>1950</ymin>
			<xmax>1292</xmax>
			<ymax>2011</ymax>
		</bndbox>
	</object>
	<object>
		<name>0.853145</name>
		<pose>Unspecified</pose>
		<truncated>0</truncated>
		<difficult>0</difficult>
		<bndbox>
			<xmin>251</xmin>
			<ymin>1861</ymin>
			<xmax>442</xmax>
			<ymax>1927</ymax>
		</bndbox>
	</object>
	<object>
		<name>0.8832619</name>
		<pose>Unspecified</pose>
		<truncated>0</truncated>
		<difficult>0</difficult>
		<bndbox>
			<xmin>87</xmin>
			<ymin>1857</ymin>
			<xmax>213</xmax>
			<ymax>1936</ymax>
		</bndbox>
	</object>
	<object>
		<name>0.8844893</name>
		<pose>Unspecified</pose>
		<truncated>0</truncated>
		<difficult>0</difficult>
		<bndbox>
			<xmin>482</xmin>
			<ymin>1854</ymin>
			<xmax>632</xmax>
			<ymax>1923</ymax>
		</bndbox>
	</object>
	<object>
		<name>0.85814303</name>
		<pose>Unspecified</pose>
		<truncated>0</truncated>
		<difficult>0</difficult>
		<bndbox>
			<xmin>1469</xmin>
			<ymin>1851</ymin>
			<xmax>1719</xmax>
			<ymax>1911</ymax>
		</bndbox>
	</object>
	<object>
		<name>0.72344595</name>
		<pose>Unspecified</pose>
		<truncated>0</truncated>
		<difficult>0</difficult>
		<bndbox>
			<xmin>1262</xmin>
			<ymin>1844</ymin>
			<xmax>1300</xmax>
			<ymax>1913</ymax>
		</bndbox>
	</object>
	<object>
		<name>0.9154894</name>
		<pose>Unspecified</pose>
		<truncated>0</truncated>
		<difficult>0</difficult>
		<bndbox>
			<xmin>406</xmin>
			<ymin>1773</ymin>
			<xmax>523</xmax>
			<ymax>1819</ymax>
		</bndbox>
	</object>
	<object>
		<name>0.8922595</name>
		<pose>Unspecified</pose>
		<truncated>0</truncated>
		<difficult>0</difficult>
		<bndbox>
			<xmin>87</xmin>
			<ymin>1757</ymin>
			<xmax>210</xmax>
			<ymax>1838</ymax>
		</bndbox>
	</object>
	<object>
		<name>0.90409404</name>
		<pose>Unspecified</pose>
		<truncated>0</truncated>
		<difficult>0</difficult>
		<bndbox>
			<xmin>240</xmin>
			<ymin>1756</ymin>
			<xmax>370</xmax>
			<ymax>1836</ymax>
		</bndbox>
	</object>
	<object>
		<name>0.92230415</name>
		<pose>Unspecified</pose>
		<truncated>0</truncated>
		<difficult>0</difficult>
		<bndbox>
			<xmin>559</xmin>
			<ymin>1752</ymin>
			<xmax>680</xmax>
			<ymax>1824</ymax>
		</bndbox>
	</object>
	<object>
		<name>0.8650052</name>
		<pose>Unspecified</pose>
		<truncated>0</truncated>
		<difficult>0</difficult>
		<bndbox>
			<xmin>717</xmin>
			<ymin>1748</ymin>
			<xmax>870</xmax>
			<ymax>1828</ymax>
		</bndbox>
	</object>
	<object>
		<name>0.8306781</name>
		<pose>Unspecified</pose>
		<truncated>0</truncated>
		<difficult>0</difficult>
		<bndbox>
			<xmin>1463</xmin>
			<ymin>1749</ymin>
			<xmax>1718</xmax>
			<ymax>1815</ymax>
		</bndbox>
	</object>
	<object>
		<name>0.391744</name>
		<pose>Unspecified</pose>
		<truncated>0</truncated>
		<difficult>0</difficult>
		<bndbox>
			<xmin>1270</xmin>
			<ymin>1651</ymin>
			<xmax>1304</xmax>
			<ymax>1714</ymax>
		</bndbox>
	</object>
	<object>
		<name>0.8893189</name>
		<pose>Unspecified</pose>
		<truncated>0</truncated>
		<difficult>0</difficult>
		<bndbox>
			<xmin>202</xmin>
			<ymin>1670</ymin>
			<xmax>289</xmax>
			<ymax>1726</ymax>
		</bndbox>
	</object>
	<object>
		<name>0.86542135</name>
		<pose>Unspecified</pose>
		<truncated>0</truncated>
		<difficult>0</difficult>
		<bndbox>
			<xmin>322</xmin>
			<ymin>1654</ymin>
			<xmax>512</xmax>
			<ymax>1721</ymax>
		</bndbox>
	</object>
	<object>
		<name>0.8799741</name>
		<pose>Unspecified</pose>
		<truncated>0</truncated>
		<difficult>0</difficult>
		<bndbox>
			<xmin>553</xmin>
			<ymin>1649</ymin>
			<xmax>682</xmax>
			<ymax>1734</ymax>
		</bndbox>
	</object>
	<object>
		<name>0.8612364</name>
		<pose>Unspecified</pose>
		<truncated>0</truncated>
		<difficult>0</difficult>
		<bndbox>
			<xmin>1461</xmin>
			<ymin>1650</ymin>
			<xmax>1717</xmax>
			<ymax>1710</ymax>
		</bndbox>
	</object>
	<object>
		<name>0.89254034</name>
		<pose>Unspecified</pose>
		<truncated>0</truncated>
		<difficult>0</difficult>
		<bndbox>
			<xmin>81</xmin>
			<ymin>1647</ymin>
			<xmax>171</xmax>
			<ymax>1731</ymax>
		</bndbox>
	</object>
	<object>
		<name>0.88151026</name>
		<pose>Unspecified</pose>
		<truncated>0</truncated>
		<difficult>0</difficult>
		<bndbox>
			<xmin>78</xmin>
			<ymin>1552</ymin>
			<xmax>209</xmax>
			<ymax>1637</ymax>
		</bndbox>
	</object>
	<object>
		<name>0.9038091</name>
		<pose>Unspecified</pose>
		<truncated>0</truncated>
		<difficult>0</difficult>
		<bndbox>
			<xmin>358</xmin>
			<ymin>1550</ymin>
			<xmax>526</xmax>
			<ymax>1631</ymax>
		</bndbox>
	</object>
	<object>
		<name>0.89532286</name>
		<pose>Unspecified</pose>
		<truncated>0</truncated>
		<difficult>0</difficult>
		<bndbox>
			<xmin>235</xmin>
			<ymin>1550</ymin>
			<xmax>325</xmax>
			<ymax>1636</ymax>
		</bndbox>
	</object>
	<object>
		<name>0.9329189</name>
		<pose>Unspecified</pose>
		<truncated>0</truncated>
		<difficult>0</difficult>
		<bndbox>
			<xmin>556</xmin>
			<ymin>1547</ymin>
			<xmax>669</xmax>
			<ymax>1622</ymax>
		</bndbox>
	</object>
	<object>
		<name>0.84665227</name>
		<pose>Unspecified</pose>
		<truncated>0</truncated>
		<difficult>0</difficult>
		<bndbox>
			<xmin>1466</xmin>
			<ymin>1544</ymin>
			<xmax>1721</xmax>
			<ymax>1614</ymax>
		</bndbox>
	</object>
	<object>
		<name>0.9052247</name>
		<pose>Unspecified</pose>
		<truncated>0</truncated>
		<difficult>0</difficult>
		<bndbox>
			<xmin>233</xmin>
			<ymin>1347</ymin>
			<xmax>360</xmax>
			<ymax>1420</ymax>
		</bndbox>
	</object>
	<object>
		<name>0.89777476</name>
		<pose>Unspecified</pose>
		<truncated>0</truncated>
		<difficult>0</difficult>
		<bndbox>
			<xmin>81</xmin>
			<ymin>1345</ymin>
			<xmax>207</xmax>
			<ymax>1424</ymax>
		</bndbox>
	</object>
	<object>
		<name>0.9226079</name>
		<pose>Unspecified</pose>
		<truncated>0</truncated>
		<difficult>0</difficult>
		<bndbox>
			<xmin>1567</xmin>
			<ymin>1337</ymin>
			<xmax>1726</xmax>
			<ymax>1418</ymax>
		</bndbox>
	</object>
	<object>
		<name>0.8744972</name>
		<pose>Unspecified</pose>
		<truncated>0</truncated>
		<difficult>0</difficult>
		<bndbox>
			<xmin>1216</xmin>
			<ymin>1333</ymin>
			<xmax>1342</xmax>
			<ymax>1420</ymax>
		</bndbox>
	</object>
	<object>
		<name>0.84031755</name>
		<pose>Unspecified</pose>
		<truncated>0</truncated>
		<difficult>0</difficult>
		<bndbox>
			<xmin>279</xmin>
			<ymin>1153</ymin>
			<xmax>359</xmax>
			<ymax>1224</ymax>
		</bndbox>
	</object>
	<object>
		<name>0.8816077</name>
		<pose>Unspecified</pose>
		<truncated>0</truncated>
		<difficult>0</difficult>
		<bndbox>
			<xmin>75</xmin>
			<ymin>1148</ymin>
			<xmax>238</xmax>
			<ymax>1230</ymax>
		</bndbox>
	</object>
	<object>
		<name>0.89494884</name>
		<pose>Unspecified</pose>
		<truncated>0</truncated>
		<difficult>0</difficult>
		<bndbox>
			<xmin>439</xmin>
			<ymin>1143</ymin>
			<xmax>593</xmax>
			<ymax>1213</ymax>
		</bndbox>
	</object>
	<object>
		<name>0.73227245</name>
		<pose>Unspecified</pose>
		<truncated>0</truncated>
		<difficult>0</difficult>
		<bndbox>
			<xmin>1541</xmin>
			<ymin>1138</ymin>
			<xmax>1650</xmax>
			<ymax>1209</ymax>
		</bndbox>
	</object>
	<object>
		<name>0.89885336</name>
		<pose>Unspecified</pose>
		<truncated>0</truncated>
		<difficult>0</difficult>
		<bndbox>
			<xmin>1370</xmin>
			<ymin>1137</ymin>
			<xmax>1496</xmax>
			<ymax>1208</ymax>
		</bndbox>
	</object>
	<object>
		<name>0.7731406</name>
		<pose>Unspecified</pose>
		<truncated>0</truncated>
		<difficult>0</difficult>
		<bndbox>
			<xmin>626</xmin>
			<ymin>1137</ymin>
			<xmax>674</xmax>
			<ymax>1211</ymax>
		</bndbox>
	</object>
	<object>
		<name>0.70183855</name>
		<pose>Unspecified</pose>
		<truncated>0</truncated>
		<difficult>0</difficult>
		<bndbox>
			<xmin>1681</xmin>
			<ymin>1134</ymin>
			<xmax>1732</xmax>
			<ymax>1205</ymax>
		</bndbox>
	</object>
	<object>
		<name>0.37710583</name>
		<pose>Unspecified</pose>
		<truncated>0</truncated>
		<difficult>0</difficult>
		<bndbox>
			<xmin>326</xmin>
			<ymin>1050</ymin>
			<xmax>354</xmax>
			<ymax>1106</ymax>
		</bndbox>
	</object>
	<object>
		<name>0.42265728</name>
		<pose>Unspecified</pose>
		<truncated>0</truncated>
		<difficult>0</difficult>
		<bndbox>
			<xmin>1622</xmin>
			<ymin>1038</ymin>
			<xmax>1641</xmax>
			<ymax>1093</ymax>
		</bndbox>
	</object>
	<object>
		<name>0.9235654</name>
		<pose>Unspecified</pose>
		<truncated>0</truncated>
		<difficult>0</difficult>
		<bndbox>
			<xmin>75</xmin>
			<ymin>1045</ymin>
			<xmax>202</xmax>
			<ymax>1116</ymax>
		</bndbox>
	</object>
	<object>
		<name>0.8560417</name>
		<pose>Unspecified</pose>
		<truncated>0</truncated>
		<difficult>0</difficult>
		<bndbox>
			<xmin>403</xmin>
			<ymin>1042</ymin>
			<xmax>591</xmax>
			<ymax>1110</ymax>
		</bndbox>
	</object>
	<object>
		<name>0.90978897</name>
		<pose>Unspecified</pose>
		<truncated>0</truncated>
		<difficult>0</difficult>
		<bndbox>
			<xmin>229</xmin>
			<ymin>1043</ymin>
			<xmax>324</xmax>
			<ymax>1115</ymax>
		</bndbox>
	</object>
	<object>
		<name>0.86025774</name>
		<pose>Unspecified</pose>
		<truncated>0</truncated>
		<difficult>0</difficult>
		<bndbox>
			<xmin>1414</xmin>
			<ymin>1037</ymin>
			<xmax>1607</xmax>
			<ymax>1103</ymax>
		</bndbox>
	</object>
	<object>
		<name>0.8954395</name>
		<pose>Unspecified</pose>
		<truncated>0</truncated>
		<difficult>0</difficult>
		<bndbox>
			<xmin>621</xmin>
			<ymin>1034</ymin>
			<xmax>714</xmax>
			<ymax>1113</ymax>
		</bndbox>
	</object>
	<object>
		<name>0.8032692</name>
		<pose>Unspecified</pose>
		<truncated>0</truncated>
		<difficult>0</difficult>
		<bndbox>
			<xmin>1684</xmin>
			<ymin>1036</ymin>
			<xmax>1728</xmax>
			<ymax>1102</ymax>
		</bndbox>
	</object>
	<object>
		<name>0.88163054</name>
		<pose>Unspecified</pose>
		<truncated>0</truncated>
		<difficult>0</difficult>
		<bndbox>
			<xmin>1294</xmin>
			<ymin>1028</ymin>
			<xmax>1379</xmax>
			<ymax>1109</ymax>
		</bndbox>
	</object>
	<object>
		<name>0.52695507</name>
		<pose>Unspecified</pose>
		<truncated>0</truncated>
		<difficult>0</difficult>
		<bndbox>
			<xmin>247</xmin>
			<ymin>951</ymin>
			<xmax>266</xmax>
			<ymax>1007</ymax>
		</bndbox>
	</object>
	<object>
		<name>0.57086176</name>
		<pose>Unspecified</pose>
		<truncated>0</truncated>
		<difficult>0</difficult>
		<bndbox>
			<xmin>1424</xmin>
			<ymin>943</ymin>
			<xmax>1447</xmax>
			<ymax>997</ymax>
		</bndbox>
	</object>
	<object>
		<name>0.82307595</name>
		<pose>Unspecified</pose>
		<truncated>0</truncated>
		<difficult>0</difficult>
		<bndbox>
			<xmin>73</xmin>
			<ymin>944</ymin>
			<xmax>240</xmax>
			<ymax>1026</ymax>
		</bndbox>
	</object>
	<object>
		<name>0.80395335</name>
		<pose>Unspecified</pose>
		<truncated>0</truncated>
		<difficult>0</difficult>
		<bndbox>
			<xmin>308</xmin>
			<ymin>941</ymin>
			<xmax>704</xmax>
			<ymax>1010</ymax>
		</bndbox>
	</object>
	<object>
		<name>0.8772071</name>
		<pose>Unspecified</pose>
		<truncated>0</truncated>
		<difficult>0</difficult>
		<bndbox>
			<xmin>1493</xmin>
			<ymin>939</ymin>
			<xmax>1721</xmax>
			<ymax>1000</ymax>
		</bndbox>
	</object>
	<object>
		<name>0.8841531</name>
		<pose>Unspecified</pose>
		<truncated>0</truncated>
		<difficult>0</difficult>
		<bndbox>
			<xmin>1219</xmin>
			<ymin>939</ymin>
			<xmax>1405</xmax>
			<ymax>1001</ymax>
		</bndbox>
	</object>
	<object>
		<name>0.89679193</name>
		<pose>Unspecified</pose>
		<truncated>0</truncated>
		<difficult>0</difficult>
		<bndbox>
			<xmin>1100</xmin>
			<ymin>930</ymin>
			<xmax>1184</xmax>
			<ymax>1009</ymax>
		</bndbox>
	</object>
	<object>
		<name>0.5459992</name>
		<pose>Unspecified</pose>
		<truncated>0</truncated>
		<difficult>0</difficult>
		<bndbox>
			<xmin>202</xmin>
			<ymin>849</ymin>
			<xmax>224</xmax>
			<ymax>907</ymax>
		</bndbox>
	</object>
	<object>
		<name>0.5269637</name>
		<pose>Unspecified</pose>
		<truncated>0</truncated>
		<difficult>0</difficult>
		<bndbox>
			<xmin>1346</xmin>
			<ymin>838</ymin>
			<xmax>1364</xmax>
			<ymax>894</ymax>
		</bndbox>
	</object>
	<object>
		<name>0.9118696</name>
		<pose>Unspecified</pose>
		<truncated>0</truncated>
		<difficult>0</difficult>
		<bndbox>
			<xmin>67</xmin>
			<ymin>840</ymin>
			<xmax>196</xmax>
			<ymax>917</ymax>
		</bndbox>
	</object>
	<object>
		<name>0.89017284</name>
		<pose>Unspecified</pose>
		<truncated>0</truncated>
		<difficult>0</difficult>
		<bndbox>
			<xmin>1141</xmin>
			<ymin>838</ymin>
			<xmax>1329</xmax>
			<ymax>900</ymax>
		</bndbox>
	</object>
	<object>
		<name>0.8212147</name>
		<pose>Unspecified</pose>
		<truncated>0</truncated>
		<difficult>0</difficult>
		<bndbox>
			<xmin>1412</xmin>
			<ymin>833</ymin>
			<xmax>1723</xmax>
			<ymax>899</ymax>
		</bndbox>
	</object>
	<object>
		<name>0.89776105</name>
		<pose>Unspecified</pose>
		<truncated>0</truncated>
		<difficult>0</difficult>
		<bndbox>
			<xmin>258</xmin>
			<ymin>835</ymin>
			<xmax>355</xmax>
			<ymax>916</ymax>
		</bndbox>
	</object>
	<object>
		<name>0.91268677</name>
		<pose>Unspecified</pose>
		<truncated>0</truncated>
		<difficult>0</difficult>
		<bndbox>
			<xmin>1019</xmin>
			<ymin>826</ymin>
			<xmax>1104</xmax>
			<ymax>906</ymax>
		</bndbox>
	</object>
	<object>
		<name>0.35219672</name>
		<pose>Unspecified</pose>
		<truncated>0</truncated>
		<difficult>0</difficult>
		<bndbox>
			<xmin>819</xmin>
			<ymin>673</ymin>
			<xmax>1020</xmax>
			<ymax>813</ymax>
		</bndbox>
	</object>
	<object>
		<name>0.70000756</name>
		<pose>Unspecified</pose>
		<truncated>0</truncated>
		<difficult>0</difficult>
		<bndbox>
			<xmin>577</xmin>
			<ymin>671</ymin>
			<xmax>772</xmax>
			<ymax>815</ymax>
		</bndbox>
	</object>
	<object>
		<name>0.60347325</name>
		<pose>Unspecified</pose>
		<truncated>0</truncated>
		<difficult>0</difficult>
		<bndbox>
			<xmin>1060</xmin>
			<ymin>662</ymin>
			<xmax>1217</xmax>
			<ymax>813</ymax>
		</bndbox>
	</object>
	<object>
		<name>0.8012026</name>
		<pose>Unspecified</pose>
		<truncated>0</truncated>
		<difficult>0</difficult>
		<bndbox>
			<xmin>733</xmin>
			<ymin>563</ymin>
			<xmax>1257</xmax>
			<ymax>633</ymax>
		</bndbox>
	</object>
	<object>
		<name>0.7622419</name>
		<pose>Unspecified</pose>
		<truncated>0</truncated>
		<difficult>0</difficult>
		<bndbox>
			<xmin>547</xmin>
			<ymin>562</ymin>
			<xmax>691</xmax>
			<ymax>640</ymax>
		</bndbox>
	</object>
	<object>
		<name>0.55567765</name>
		<pose>Unspecified</pose>
		<truncated>0</truncated>
		<difficult>0</difficult>
		<bndbox>
			<xmin>556</xmin>
			<ymin>464</ymin>
			<xmax>577</xmax>
			<ymax>524</ymax>
		</bndbox>
	</object>
	<object>
		<name>0.61221266</name>
		<pose>Unspecified</pose>
		<truncated>0</truncated>
		<difficult>0</difficult>
		<bndbox>
			<xmin>628</xmin>
			<ymin>459</ymin>
			<xmax>1376</xmax>
			<ymax>536</ymax>
		</bndbox>
	</object>
	<object>
		<name>0.8938132</name>
		<pose>Unspecified</pose>
		<truncated>0</truncated>
		<difficult>0</difficult>
		<bndbox>
			<xmin>420</xmin>
			<ymin>462</ymin>
			<xmax>546</xmax>
			<ymax>535</ymax>
		</bndbox>
	</object>
	<object>
		<name>0.7835901</name>
		<pose>Unspecified</pose>
		<truncated>0</truncated>
		<difficult>0</difficult>
		<bndbox>
			<xmin>140</xmin>
			<ymin>358</ymin>
			<xmax>426</xmax>
			<ymax>434</ymax>
		</bndbox>
	</object>
	<object>
		<name>0.72050273</name>
		<pose>Unspecified</pose>
		<truncated>0</truncated>
		<difficult>0</difficult>
		<bndbox>
			<xmin>853</xmin>
			<ymin>363</ymin>
			<xmax>894</xmax>
			<ymax>423</ymax>
		</bndbox>
	</object>
	<object>
		<name>0.8798292</name>
		<pose>Unspecified</pose>
		<truncated>0</truncated>
		<difficult>0</difficult>
		<bndbox>
			<xmin>662</xmin>
			<ymin>350</ymin>
			<xmax>813</xmax>
			<ymax>435</ymax>
		</bndbox>
	</object>
	<object>
		<name>0.8814465</name>
		<pose>Unspecified</pose>
		<truncated>0</truncated>
		<difficult>0</difficult>
		<bndbox>
			<xmin>457</xmin>
			<ymin>351</ymin>
			<xmax>625</xmax>
			<ymax>430</ymax>
		</bndbox>
	</object>
	<object>
		<name>0.87043536</name>
		<pose>Unspecified</pose>
		<truncated>0</truncated>
		<difficult>0</difficult>
		<bndbox>
			<xmin>1091</xmin>
			<ymin>349</ymin>
			<xmax>1258</xmax>
			<ymax>430</ymax>
		</bndbox>
	</object>
	<object>
		<name>0.80753696</name>
		<pose>Unspecified</pose>
		<truncated>0</truncated>
		<difficult>0</difficult>
		<bndbox>
			<xmin>1293</xmin>
			<ymin>359</ymin>
			<xmax>1336</xmax>
			<ymax>421</ymax>
		</bndbox>
	</object>
	<object>
		<name>0.92604285</name>
		<pose>Unspecified</pose>
		<truncated>0</truncated>
		<difficult>0</difficult>
		<bndbox>
			<xmin>929</xmin>
			<ymin>353</ymin>
			<xmax>1060</xmax>
			<ymax>425</ymax>
		</bndbox>
	</object>
	<object>
		<name>0.82905215</name>
		<pose>Unspecified</pose>
		<truncated>0</truncated>
		<difficult>0</difficult>
		<bndbox>
			<xmin>1494</xmin>
			<ymin>348</ymin>
			<xmax>1602</xmax>
			<ymax>434</ymax>
		</bndbox>
	</object>
	<object>
		<name>0.91071784</name>
		<pose>Unspecified</pose>
		<truncated>0</truncated>
		<difficult>0</difficult>
		<bndbox>
			<xmin>1368</xmin>
			<ymin>349</ymin>
			<xmax>1449</xmax>
			<ymax>430</ymax>
		</bndbox>
	</object>
	<object>
		<name>0.6637541</name>
		<pose>Unspecified</pose>
		<truncated>0</truncated>
		<difficult>0</difficult>
		<bndbox>
			<xmin>1214</xmin>
			<ymin>198</ymin>
			<xmax>1287</xmax>
			<ymax>328</ymax>
		</bndbox>
	</object>
	<object>
		<name>0.7728079</name>
		<pose>Unspecified</pose>
		<truncated>0</truncated>
		<difficult>0</difficult>
		<bndbox>
			<xmin>465</xmin>
			<ymin>225</ymin>
			<xmax>624</xmax>
			<ymax>345</ymax>
		</bndbox>
	</object>
	<object>
		<name>0.77001315</name>
		<pose>Unspecified</pose>
		<truncated>0</truncated>
		<difficult>0</difficult>
		<bndbox>
			<xmin>1334</xmin>
			<ymin>191</ymin>
			<xmax>1441</xmax>
			<ymax>340</ymax>
		</bndbox>
	</object>
	<object>
		<name>0.86416566</name>
		<pose>Unspecified</pose>
		<truncated>0</truncated>
		<difficult>0</difficult>
		<bndbox>
			<xmin>288</xmin>
			<ymin>199</ymin>
			<xmax>433</xmax>
			<ymax>344</ymax>
		</bndbox>
	</object>
	<object>
		<name>0.6868725</name>
		<pose>Unspecified</pose>
		<truncated>0</truncated>
		<difficult>0</difficult>
		<bndbox>
			<xmin>781</xmin>
			<ymin>201</ymin>
			<xmax>1178</xmax>
			<ymax>337</ymax>
		</bndbox>
	</object>
	<object>
		<name>0.65361714</name>
		<pose>Unspecified</pose>
		<truncated>0</truncated>
		<difficult>0</difficult>
		<bndbox>
			<xmin>648</xmin>
			<ymin>198</ymin>
			<xmax>732</xmax>
			<ymax>331</ymax>
		</bndbox>
	</object>
	<object>
		<name>1</name>
		<pose>Unspecified</pose>
		<truncated>0</truncated>
		<difficult>0</difficult>
		<bndbox>
			<xmin>366</xmin>
			<ymin>1149</ymin>
			<xmax>387</xmax>
			<ymax>1206</ymax>
		</bndbox>
	</object>
	<object>
		<name>1</name>
		<pose>Unspecified</pose>
		<truncated>0</truncated>
		<difficult>0</difficult>
		<bndbox>
			<xmin>1270</xmin>
			<ymin>1538</ymin>
			<xmax>1296</xmax>
			<ymax>1619</ymax>
		</bndbox>
	</object>
	<object>
		<name>1</name>
		<pose>Unspecified</pose>
		<truncated>0</truncated>
		<difficult>0</difficult>
		<bndbox>
			<xmin>1265</xmin>
			<ymin>1747</ymin>
			<xmax>1295</xmax>
			<ymax>1813</ymax>
		</bndbox>
	</object>
</annotation>
